Metadata-Version: 2.1
Name: modoboa-pdfcredentials
Version: 1.5.0
Summary: Generate PDF documents containing user credentials
Home-page: http://modoboa.org/
Author: Antoine Nguyen
Author-email: tonio@ngyn.org
License: MIT
Keywords: email
Platform: UNKNOWN
Classifier: Development Status :: 5 - Production/Stable
Classifier: Environment :: Web Environment
Classifier: Framework :: Django :: 2.2
Classifier: Intended Audience :: System Administrators
Classifier: License :: OSI Approved :: MIT License
Classifier: Operating System :: OS Independent
Classifier: Programming Language :: Python :: 3
Classifier: Programming Language :: Python :: 3.5
Classifier: Programming Language :: Python :: 3.6
Classifier: Programming Language :: Python :: 3.7
Classifier: Topic :: Communications :: Email
Classifier: Topic :: Internet :: WWW/HTTP
License-File: LICENSE
Requires-Dist: modoboa (>=2.0.0)
Requires-Dist: reportlab
